cache.py
cleanup.py
config.py
describer.py
generator.py
main.py
storage.py
utils.py
validator.py
mmodal_mcp-0.8.5.dist-info/licenses/LICENSE
mmodal_mcp-0.8.5.dist-info/METADATA
mmodal_mcp-0.8.5.dist-info/WHEEL
mmodal_mcp-0.8.5.dist-info/entry_points.txt
mmodal_mcp-0.8.5.dist-info/top_level.txt
mmodal_mcp-0.8.5.dist-info/RECORD
