Metadata-Version: 2.4
Name: mmodal-mcp
Version: 0.8.5
Summary: Multimodal MCP server for generating images and describing assets across providers.
Author: mmodal-mcp contributors
License: MIT
Requires-Python: >=3.10
License-File: LICENSE
Requires-Dist: mcp[cli]>=1.20.0
Requires-Dist: pillow>=12.0.0
Requires-Dist: pydantic>=2.12.3
Requires-Dist: pydantic-settings>=2.6.1
Requires-Dist: python-dotenv>=1.2.1
Requires-Dist: python-docx>=1.1.2
Requires-Dist: python-pptx>=0.6.23
Requires-Dist: aiofiles>=25.1.0
Requires-Dist: litellm>=1.48.6
Requires-Dist: openpyxl>=3.1.5
Requires-Dist: pypdf>=5.1.0
Dynamic: license-file
